{
    "type": "postgres",
    "url": "postgres://xtauquohetpeca:f39b344a058861ee727fc14d2ce71e29b526547a64c9925cce0c0310ddafe0ee@ec2-3-227-154-49.compute-1.amazonaws.com:5432/dd3kjktgjknm1n",
    "ssl": {
        "rejectUnauthorized": false
    },
    "entities": [
        "./src/modules/**/entities/*.ts"
    ],
    "migrations": [
        "./src/shared/infra/typeorm/migrations/*.ts"
    ],
    "migrationsTableName": "_migrations",
    "cli": {
        "migrationsDir": "./src/shared/infra/typeorm/migrations"
    }
}